deepview_tensorflow/__main__.py
deepview_tensorflow/conversion_tflite.py
deepview_tensorflow/assets/image.png
deepview_tensorflow/assets/info.html
deepview_converter_tflite-2.5.23.dist-info/LICENSE.txt
deepview_converter_tflite-2.5.23.dist-info/METADATA
deepview_converter_tflite-2.5.23.dist-info/WHEEL
deepview_converter_tflite-2.5.23.dist-info/entry_points.txt
deepview_converter_tflite-2.5.23.dist-info/top_level.txt
deepview_converter_tflite-2.5.23.dist-info/RECORD
