Metadata-Version: 2.1
Name: deepview-converter-tflite
Version: 2.5.23
Summary: DeepView Converter for TensorFlow Lite
Home-page: https://www.au-zone.com
Author: Au-Zone
Author-email: support@au-zone.com
License: PROPRIETARY
Platform: UNKNOWN
Requires-Dist: deepview-converter (~=2.6.7)
Requires-Dist: onnx-tf (~=1.10.0)
Provides-Extra: tensorflow
Requires-Dist: wheel ; extra == 'tensorflow'
